Metadata-Version: 2.1
Name: plover-current-time
Version: 1.0.1
Summary: Plover plugin for inserting the current time in an strftime format
Home-page: https://github.com/EPLHREU/plover-current-time
Author: Emily Easteal
Author-email: emily@easteal.dev
License: UNKNOWN
Keywords: plover plover_plugin
Platform: UNKNOWN
Classifier: Programming Language :: Python :: 3.6
Classifier: Programming Language :: Python :: 3.7
Classifier: Programming Language :: Python :: 3.8
Classifier: Programming Language :: Python :: 3.9
